clouds_aws/__init__.py
clouds_aws/cli/__init__.py
clouds_aws/cli/change.py
clouds_aws/cli/clone.py
clouds_aws/cli/common.py
clouds_aws/cli/console.py
clouds_aws/cli/delete.py
clouds_aws/cli/describe.py
clouds_aws/cli/dump.py
clouds_aws/cli/events.py
clouds_aws/cli/format.py
clouds_aws/cli/list.py
clouds_aws/cli/update.py
clouds_aws/cli/validate.py
clouds_aws/local_stack/__init__.py
clouds_aws/local_stack/helpers.py
clouds_aws/local_stack/parameters.py
clouds_aws/local_stack/template.py
clouds_aws/remote_stack/__init__.py
clouds_aws/remote_stack/aws_client.py
clouds_aws/remote_stack/change_set.py
clouds_aws-0.4.3.dist-info/licenses/COPYING
clouds_aws-0.4.3.dist-info/licenses/LICENSE
clouds_aws-0.4.3.dist-info/METADATA
clouds_aws-0.4.3.dist-info/WHEEL
clouds_aws-0.4.3.dist-info/entry_points.txt
clouds_aws-0.4.3.dist-info/top_level.txt
clouds_aws-0.4.3.dist-info/RECORD
