Metadata-Version: 2.4
Name: clouds-aws
Version: 0.4.3
Summary: A tool for easy handling of AWS CloudFormation stacks as code.
Home-page: https://github.com/elias5000/clouds-aws
Author: Frank Wittig
Author-email: frank@e5k.de
License: Apache License, Version 2.0
Keywords: aws cloudformation devops
Classifier: Development Status :: 5 - Production/Stable
Classifier: Environment :: Console
Classifier: Intended Audience :: Developers
Classifier: Intended Audience :: System Administrators
Classifier: License :: OSI Approved :: Apache Software License
Classifier: Operating System :: MacOS :: MacOS X
Classifier: Operating System :: POSIX
Classifier: Operating System :: Unix
Classifier: Programming Language :: Python :: 3
Classifier: Programming Language :: Python :: 3.9
Classifier: Programming Language :: Python :: 3.10
Classifier: Programming Language :: Python :: 3.11
Classifier: Topic :: System :: Installation/Setup
Classifier: Topic :: Utilities
License-File: LICENSE
License-File: COPYING
Requires-Dist: boto3
Requires-Dist: ruamel.yaml
Requires-Dist: tabulate
Dynamic: author
Dynamic: author-email
Dynamic: classifier
Dynamic: description
Dynamic: home-page
Dynamic: keywords
Dynamic: license
Dynamic: license-file
Dynamic: requires-dist
Dynamic: summary
